Workbook
Name aporte: Simulador!$E$19
Name forma_aporte: Simulador!$E$9
Name ListaPerfis: Perfis!$F$6:$F$8
Name patrimonio: Simulador!$E$20
Name percentual_salario: Simulador!$E$10
Name perfil: Simulador!$E$15
Name qtd_anos: Simulador!$E$12
Name rendimento_carteira: Simulador!$E$14
Name salario: Simulador!$E$8
Name sugestao_investimento: Simulador!$E$18
Name taxa_mensal: Simulador!$E$13
Name valor_mensal: Simulador!$E$11

Sheet Simulador
B2: SIMULADOR EDUCACIONAL DE INVESTIMENTOS EM FIIs
B3: Planejamento por perfil, prazo e taxa mensal
B4: Preencha as células amarelas. O simulador projeta patrimônio e dividendos por capitalização mensal. Resultados educacionais: não constituem promessa de rentabilidade, recomendação financeira ou previsão de mercado.
B7: CONFIGURAÇÕES
B8: Salário mensal | E8: 5000
B9: Forma do aporte | E9: Valor mensal
B10: Percentual do salário | E10: 0.3
B11: Valor mensal informado | E11: 200
B12: Prazo do investimento (anos) | E12: 5
B13: Taxa de rendimento mensal | E13: 0.01079
B14: Taxa mensal estimada de dividendos | E14: 0.006
B15: Perfil do investidor — selecione na lista ▼ | E15: Moderado
B17: RESULTADOS DO INVESTIMENTO
B18: Sugestão pelo percentual | E18: =salario*percentual_salario -> 1500
B19: Aporte mensal efetivo | E19: =IF(forma_aporte="% do salário",salario*percentual_salario,valor_mensal) -> 200
B20: Patrimônio no prazo | E20: =IF(qtd_anos=0,0,FV(taxa_mensal,qtd_anos*12,-aporte)) -> 16755.383
B21: Dividendos mensais estimados | E21: =patrimonio*rendimento_carteira -> 100.5323
B22: Total aportado | E22: =aporte*qtd_anos*12 -> 12000
B23: Rendimento acumulado | E23: =patrimonio-E22 -> 4755.3828
B24: Soma da alocação | E24: =SUM(D36:D41) -> 1
B26: CENÁRIOS
A27: Anos | B27: Descrição | D27: Patrimônio acumulado | E27: Dividendos mensais
A28: 2 | B28: Quanto em 2 anos? | D28: =FV(taxa_mensal,A28*12,-aporte) -> 5445.5255 | E28: =D28*rendimento_carteira -> 32.673153
A29: 5 | B29: Quanto em 5 anos? | D29: =FV(taxa_mensal,A29*12,-aporte) -> 16755.383 | E29: =D29*rendimento_carteira -> 100.5323
A30: 10 | B30: Quanto em 10 anos? | D30: =FV(taxa_mensal,A30*12,-aporte) -> 48656.843 | E30: =D30*rendimento_carteira -> 291.94106
A31: 20 | B31: Quanto em 20 anos? | D31: =FV(taxa_mensal,A31*12,-aporte) -> 225039.68 | E31: =D31*rendimento_carteira -> 1350.2381
A32: 30 | B32: Quanto em 30 anos? | D32: =FV(taxa_mensal,A32*12,-aporte) -> 864433.93 | E32: =D32*rendimento_carteira -> 5186.6036
B34: PERFIL E DISTRIBUIÇÃO DO APORTE
B35: Tipo de FII | C35: Perfil selecionado | D35: Percentual | E35: Valor mensal
B36: PAPEL | C36: =perfil -> Moderado | D36: =VLOOKUP(perfil&"-"&B36,Perfis!$A$5:$D$22,4,FALSE) -> 0.32 | E36: =D36*aporte -> 64
B37: TIJOLO | C37: =perfil -> Moderado | D37: =VLOOKUP(perfil&"-"&B37,Perfis!$A$5:$D$22,4,FALSE) -> 0.35 | E37: =D37*aporte -> 70
B38: HÍBRIDOS | C38: =perfil -> Moderado | D38: =VLOOKUP(perfil&"-"&B38,Perfis!$A$5:$D$22,4,FALSE) -> 0.08 | E38: =D38*aporte -> 16
B39: FOFs | C39: =perfil -> Moderado | D39: =VLOOKUP(perfil&"-"&B39,Perfis!$A$5:$D$22,4,FALSE) -> 0.05 | E39: =D39*aporte -> 10
B40: DESENVOLVIMENTO | C40: =perfil -> Moderado | D40: =VLOOKUP(perfil&"-"&B40,Perfis!$A$5:$D$22,4,FALSE) -> 0.1 | E40: =D40*aporte -> 20
B41: HOTELARIAS | C41: =perfil -> Moderado | D41: =VLOOKUP(perfil&"-"&B41,Perfis!$A$5:$D$22,4,FALSE) -> 0.1 | E41: =D41*aporte -> 20
B42: TOTAL | D42: =SUM(D36:D41) -> 1 | E42: =SUM(E36:E41) -> 200
B44: EVOLUÇÃO DO PATRIMÔNIO
B61: EVOLUÇÃO DOS DIVIDENDOS

Sheet Perfis
A1: BASE DE PERFIS E CONTROLES
A2: Percentuais preservados da planilha original; esta aba sustenta a lista e a distribuição do simulador.
A4: CHAVE | B4: PERFIL | C4: TIPO DE FII | D4: % | F4: CONTROLE DE CONSISTÊNCIA
A5: Conservador-PAPEL | B5: Conservador | C5: PAPEL | D5: 0.3 | F5: Perfil | G5: Total | H5: Status
A6: Conservador-TIJOLO | B6: Conservador | C6: TIJOLO | D6: 0.5 | F6: Conservador | G6: =SUMIF($B$5:$B$22,F6,$D$5:$D$22) -> 1 | H6: =IF(G6=100%,"OK","REVISAR") -> OK
A7: Conservador-HÍBRIDOS | B7: Conservador | C7: HÍBRIDOS | D7: 0.1 | F7: Moderado | G7: =SUMIF($B$5:$B$22,F7,$D$5:$D$22) -> 1 | H7: =IF(G7=100%,"OK","REVISAR") -> OK
A8: Conservador-FOFs | B8: Conservador | C8: FOFs | D8: 0.1 | F8: Agressivo | G8: =SUMIF($B$5:$B$22,F8,$D$5:$D$22) -> 1 | H8: =IF(G8=100%,"OK","REVISAR") -> OK
A9: Conservador-DESENVOLVIMENTO | B9: Conservador | C9: DESENVOLVIMENTO | D9: 0
A10: Conservador-HOTELARIAS | B10: Conservador | C10: HOTELARIAS | D10: 0
A11: Moderado-PAPEL | B11: Moderado | C11: PAPEL | D11: 0.32
A12: Moderado-TIJOLO | B12: Moderado | C12: TIJOLO | D12: 0.35
A13: Moderado-HÍBRIDOS | B13: Moderado | C13: HÍBRIDOS | D13: 0.08
A14: Moderado-FOFs | B14: Moderado | C14: FOFs | D14: 0.05
A15: Moderado-DESENVOLVIMENTO | B15: Moderado | C15: DESENVOLVIMENTO | D15: 0.1
A16: Moderado-HOTELARIAS | B16: Moderado | C16: HOTELARIAS | D16: 0.1
A17: Agressivo-PAPEL | B17: Agressivo | C17: PAPEL | D17: 0.5
A18: Agressivo-TIJOLO | B18: Agressivo | C18: TIJOLO | D18: 0.1
A19: Agressivo-HÍBRIDOS | B19: Agressivo | C19: HÍBRIDOS | D19: 0.05
A20: Agressivo-FOFs | B20: Agressivo | C20: FOFs | D20: 0.05
... A22: Agressivo-HOTELARIAS | B22: Agressivo | C22: HOTELARIAS | D22: 0.1
